<?xml version="1.0" encoding="utf-8"?>
<Defs>
	<ScenarioDef ParentName="ScenarioBase">
		<defName>DITN_Prospectors</defName>
		<label>Outcast refugees</label>
		<description>You arrived, following the dream of many, you are the first of your ship to set foot on this world. The fresh air is the first you have breathed in years, you are here now. Many of your family and friends could not make it but you did.. What will you do with your freedom?</description>

		<scenario>
			<summary>A group of settlers from a fallen world seeking security.</summary>
			<playerFaction>
				<def>PlayerFaction</def>
				<factionDef>DITN_Player</factionDef>
			</playerFaction>

			<parts>
				<li Class="ScenPart_GameStartDialog">
					<def>GameStartDialog</def>
					<text>You arrived, following the dream of many, you are the first of your ship to set foot on this world.\n\nThe fresh air is the first you have breathed in years, you are here now. Many of your family and friends could not make it but you did.\n\nWhat will you do with your freedom?</text>
					<closeSound>GameStartSting</closeSound>
				</li>

				<li Class="ScenPart_ConfigPage_ConfigureStartingPawns">
					<def>ConfigPage_ConfigureStartingPawns</def>
					<pawnCount>5</pawnCount>
					<pawnChoiceCount>8</pawnChoiceCount>
				</li>

				<li Class="ScenPart_PlayerPawnsArriveMethod">
					<def>PlayerPawnsArriveMethod</def>
					<method>DropPods</method>
					<visible>false</visible>
				</li>

				<li Class="ScenPart_ForcedHediff">
					<def>ForcedHediff</def>
					<visible>false</visible>
					<context>PlayerStarter</context>
					<chance>0.5</chance>
					<hediff>CryptosleepSickness</hediff>
					<hideOffMap>true</hideOffMap>
					<severityRange>1~1</severityRange>
				</li>

				<li Class="ScenPart_StartingThing_Defined">
					<def>StartingThing_Defined</def>
					<thingDef>DITN_LawbringerShotgun</thingDef>
					<count>1</count>					
					<quality>Normal</quality>
				</li>

				<li Class="ScenPart_StartingThing_Defined">
					<def>StartingThing_Defined</def>
					<thingDef>DITN_ServicePistol</thingDef>
					<count>1</count>
					<quality>Normal</quality>
				</li>

				<li Class="ScenPart_StartingThing_Defined">
					<def>StartingThing_Defined</def>
					<thingDef>DITN_Vibroblade</thingDef>
					<count>1</count>
					<quality>Normal</quality>
				</li>

				<li Class="ScenPart_StartingThing_Defined">
					<def>StartingThing_Defined</def>
					<thingDef>DITN_MarauderArmor</thingDef>
					<count>1</count>
					<quality>Normal</quality>
				</li>

				<li Class="ScenPart_StartingThing_Defined">
					<def>StartingThing_Defined</def>
					<thingDef>DITN_MarauderHelmet</thingDef>
					<count>1</count>
					<quality>Normal</quality>
				</li>

				<li Class="ScenPart_StartingThing_Defined">
					<def>StartingThing_Defined</def>
					<thingDef>Silver</thingDef>
					<count>400</count>
				</li>

				<li Class="ScenPart_StartingThing_Defined">
					<def>StartingThing_Defined</def>
					<thingDef>MealSurvivalPack</thingDef>
					<count>150</count>
				</li>

				<li Class="ScenPart_StartingThing_Defined">
					<def>StartingThing_Defined</def>
					<thingDef>ComponentIndustrial</thingDef>
					<count>40</count>
				</li>

				<li Class="ScenPart_StartingThing_Defined">
					<def>StartingThing_Defined</def>
					<thingDef>ComponentSpacer</thingDef>
					<count>5</count>
				</li>				

				<li Class="ScenPart_StartingThing_Defined">
					<def>StartingThing_Defined</def>
					<thingDef>MedicineIndustrial</thingDef>
					<count>60</count>
				</li>

				<li Class="ScenPart_StartingThing_Defined">
					<def>StartingThing_Defined</def>
					<thingDef>Steel</thingDef>
					<count>200</count>
				</li>

				<li Class="ScenPart_StartingThing_Defined">
					<def>StartingThing_Defined</def>
					<thingDef>WoodLog</thingDef>
					<count>300</count>
				</li>

				<!-- Needed for Scenario Start to get Early Research-->
				<li Class="ScenPart_StartingResearch">
					<def>StartingResearch</def>
					<project>DITN_FabricationBench</project>
				</li>

				<li Class="ScenPart_StartingResearch">
					<def>StartingResearch</def>
					<project>DITN_OutcastUniforms</project>
				</li>				

				 <!-- Scatter some things near player start -->
				<li Class="ScenPart_ScatterThingsNearPlayerStart">
					<def>ScatterThingsNearPlayerStart</def>
					<thingDef>Steel</thingDef>
					<count>450</count>
				</li>
				<li Class="ScenPart_ScatterThingsNearPlayerStart">
					<def>ScatterThingsNearPlayerStart</def>
					<thingDef>WoodLog</thingDef>
					<count>300</count>
				</li>      

				<!-- Scatter some things anywhere -->
				<li Class="ScenPart_ScatterThingsAnywhere">
				<def>ScatterThingsAnywhere</def>
					<thingDef>ShipChunk</thingDef>
					<allowRoofed>false</allowRoofed>
					<count>3</count>
				</li>
				<li Class="ScenPart_ScatterThingsAnywhere">
					<def>ScatterThingsAnywhere</def>
					<thingDef>Steel</thingDef>
					<count>720</count>
				</li>
				<li Class="ScenPart_ScatterThingsAnywhere">
					<def>ScatterThingsAnywhere</def>
					<thingDef>MealSurvivalPack</thingDef>
					<count>7</count>
				</li>
			</parts>
		</scenario>
	</ScenarioDef>
</Defs>