<?xml version="1.0" encoding="utf-8"?>
<Defs>

  <RulePackDef>
    <defName>DRG_PawnNamerRinger</defName>
    <rulePack>
      <rulesStrings>
        <li>r_name_male->[firstname_male] [surname]</li>
        <li>r_name_female->[firstname_female] [surname]</li>
      </rulesStrings>
      <rulesFiles>
        <li>firstname_male->Names/DRG_Ringer_Male</li>
        <li>firstname_female->Names/DRG_Ringer_Female</li>
        <li>surname->Names/DRG_Ringer_Surname</li>
      </rulesFiles>
    </rulePack>
  </RulePackDef>

</Defs>
